Metadata-Version: 2.4
Name: ragparser
Version: 1.0.5
Summary: A comprehensive document parser for RAG applications with support for PDF, DOCX, PPTX, XLSX, and more
Home-page: https://github.com/shubham7995/ragparser
Author: Shubham Shinde
Author-email: Shubham Shinde <shubhamshinde7995@gmail.com>
License: MIT License
Project-URL: Homepage, https://github.com/shubham7995/ragparser
Project-URL: Documentation, https://github.com/shubham7995/ragparser#readme
Project-URL: Repository, https://github.com/shubham7995/ragparser
Project-URL: Bug Tracker, https://github.com/shubham7995/ragparser/issues
Classifier: Development Status :: 4 - Beta
Classifier: Intended Audience :: Developers
Classifier: License :: OSI Approved :: MIT License
Classifier: Operating System :: OS Independent
Classifier: Programming Language :: Python :: 3
Classifier: Programming Language :: Python :: 3.8
Classifier: Programming Language :: Python :: 3.9
Classifier: Programming Language :: Python :: 3.10
Classifier: Programming Language :: Python :: 3.11
Classifier: Programming Language :: Python :: 3.12
Classifier: Topic :: Scientific/Engineering :: Artificial Intelligence
Classifier: Topic :: Text Processing :: Markup
Classifier: Topic :: Software Development :: Libraries :: Python Modules
Classifier: Framework :: AsyncIO
Requires-Python: >=3.8
License-File: LICENSE
Requires-Dist: aiofiles>=0.8.0
Provides-Extra: pdf
Requires-Dist: PyMuPDF>=1.23.0; extra == "pdf"
Requires-Dist: pdfplumber>=0.9.0; extra == "pdf"
Provides-Extra: office
Requires-Dist: python-docx>=0.8.11; extra == "office"
Requires-Dist: python-pptx>=0.6.21; extra == "office"
Requires-Dist: openpyxl>=3.1.0; extra == "office"
Provides-Extra: html
Requires-Dist: beautifulsoup4>=4.11.0; extra == "html"
Requires-Dist: lxml>=4.9.0; extra == "html"
Provides-Extra: ocr
Requires-Dist: pytesseract>=0.3.10; extra == "ocr"
Requires-Dist: Pillow>=9.0.0; extra == "ocr"
Provides-Extra: advanced
Requires-Dist: sentence-transformers>=2.2.0; extra == "advanced"
Requires-Dist: nltk>=3.8; extra == "advanced"
Requires-Dist: spacy>=3.5.0; extra == "advanced"
Provides-Extra: all
Requires-Dist: PyMuPDF>=1.23.0; extra == "all"
Requires-Dist: pdfplumber>=0.9.0; extra == "all"
Requires-Dist: python-docx>=0.8.11; extra == "all"
Requires-Dist: python-pptx>=0.6.21; extra == "all"
Requires-Dist: openpyxl>=3.1.0; extra == "all"
Requires-Dist: beautifulsoup4>=4.11.0; extra == "all"
Requires-Dist: lxml>=4.9.0; extra == "all"
Requires-Dist: pytesseract>=0.3.10; extra == "all"
Requires-Dist: Pillow>=9.0.0; extra == "all"
Requires-Dist: sentence-transformers>=2.2.0; extra == "all"
Requires-Dist: nltk>=3.8; extra == "all"
Requires-Dist: spacy>=3.5.0; extra == "all"
Provides-Extra: dev
Requires-Dist: pytest>=7.0; extra == "dev"
Requires-Dist: pytest-asyncio>=0.21.0; extra == "dev"
Requires-Dist: pytest-cov>=4.0.0; extra == "dev"
Requires-Dist: black>=23.0; extra == "dev"
Requires-Dist: mypy>=1.0; extra == "dev"
Requires-Dist: flake8>=6.0; extra == "dev"
Requires-Dist: pre-commit>=3.0.0; extra == "dev"
Requires-Dist: twine>=4.0.0; extra == "dev"
Provides-Extra: test
Requires-Dist: pytest>=7.0; extra == "test"
Requires-Dist: pytest-asyncio>=0.21.0; extra == "test"
Requires-Dist: pytest-cov>=4.0.0; extra == "test"
Requires-Dist: pytest-mock>=3.10.0; extra == "test"
Provides-Extra: langchain
Requires-Dist: langchain>=0.1.0; extra == "langchain"
Requires-Dist: langchain-community>=0.0.10; extra == "langchain"
Provides-Extra: llamaindex
Requires-Dist: llama-index>=0.9.0; extra == "llamaindex"
Dynamic: author
Dynamic: home-page
Dynamic: license-file
Dynamic: requires-python
